yter/__init__.py
yter/_fun.py
yter/_key.py
yter/_ytr.py
yter-3.0.1.dist-info/LICENSE
yter-3.0.1.dist-info/METADATA
yter-3.0.1.dist-info/WHEEL
yter-3.0.1.dist-info/top_level.txt
yter-3.0.1.dist-info/zip-safe
yter-3.0.1.dist-info/RECORD
