Metadata-Version: 2.1
Name: yter
Version: 3.0.1
Summary: Clever, quick iterators that make your smile whiter
Home-page: https://gitlab.com/shredwheat/yter
Author: Peter Shinners
Author-email: pete@shinners.org
License: MIT
Keywords: iterator itertools
Classifier: Development Status :: 5 - Production/Stable
Classifier: Intended Audience :: Developers
Classifier: License :: OSI Approved :: MIT License
Classifier: Programming Language :: Python :: 2
Classifier: Programming Language :: Python :: 3
Classifier: Topic :: Software Development :: Libraries
License-File: LICENSE
